{"type":"PR","pr":{"number":280,"head":"c6689455dad96eef1ab84fdfb5bd9212494af695"},"user":"epifany.bojanowska","status":"draft","branch":"cms/ui-designer","collection":"career","title":"UI Designer","description":"We are looking for talented UI designer to help us build great digital products.","objects":{"entry":{"path":"_career/ui-designer.md","sha":"fe257228c8584c1091b9ecddc12319ce79004c67"},"files":[{"path":"/assets/images/image.png","sha":"8797c91f750421620c811e0f2dd866238115f99c"}]},"timeStamp":"2019-01-17T10:16:33.270Z"}